[
    {
        "Name": "Ethereum",
        "Symbol": "ETH",
        "Paire": "ETHUSDT",
        "OpenTime": "2023-12-09 20:58:00",
        "Open": 2352.97,
        "High": 2353.2,
        "Low": 2352.96,
        "Close": 2353.19,
        "Volume": 8.752,
        "IA": "Acheter"
    },
    {
        "Name": "Bitcoin",
        "Symbol": "BTC",
        "Paire": "BTCUSDT",
        "OpenTime": "2023-12-09 20:58:00",
        "Open": 43983.99,
        "High": 43983.99,
        "Low": 43983.98,
        "Close": 43983.98,
        "Volume": 0.64125,
        "IA": "Acheter"
    }
]