{
    "BTC/USDT": "Neutral",
    "XMR/USDT": "Vente",
    "ICP/USDT": "Neutral",
    "BCH/USDT": "Neutral",
    "DAI/USDT": "Neutral",
    "BNB/USDT": "Neutral",
    "ETH/USDT": "Neutral",
    "UNI/USDT": "Achat",
    "MATIC/USDT": "Neutral",
    "XRP/USDT": "Achat",
    "DOT/USDT": "Vente",
    "AVAX/USDT": "Vente",
    "DOGE/USDT": "Neutral",
    "LINK/USDT": "Achat",
    "SOL/USDT": "Vente",
    "LTC/USDT": "Vente",
    "ADA/USDT": "Neutral",
    "ATOM/USDT": "Vente",
    "TRX/USDT": "Vente",
    "SHIB/USDT": "Neutral"
}