[
    {
        "Name": "Ethereum",
        "Symbol": "ETH",
        "Paire": "ETHUSDT",
        "OpenTime": "2023-12-09 20:15:00",
        "Open": 2355.0,
        "High": 2355.01,
        "Low": 2353.6,
        "Close": 2353.6,
        "Volume": 49.6455,
        "IA": "Acheter"
    },
    {
        "Name": "Bitcoin",
        "Symbol": "BTC",
        "Paire": "BTCUSDT",
        "OpenTime": "2023-12-09 20:15:00",
        "Open": 43896.11,
        "High": 43896.12,
        "Low": 43882.0,
        "Close": 43882.0,
        "Volume": 10.52303,
        "IA": "Acheter"
    }
]